ocrd_tesserocr/__init__.py
ocrd_tesserocr/binarize.py
ocrd_tesserocr/cli.py
ocrd_tesserocr/common.py
ocrd_tesserocr/crop.py
ocrd_tesserocr/deskew.py
ocrd_tesserocr/fontshape.py
ocrd_tesserocr/ocrd-tool.json
ocrd_tesserocr/recognize.py
ocrd_tesserocr/segment.py
ocrd_tesserocr/segment_line.py
ocrd_tesserocr/segment_region.py
ocrd_tesserocr/segment_table.py
ocrd_tesserocr/segment_word.py
ocrd_tesserocr-0.20.1.dist-info/LICENSE
ocrd_tesserocr-0.20.1.dist-info/METADATA
ocrd_tesserocr-0.20.1.dist-info/WHEEL
ocrd_tesserocr-0.20.1.dist-info/entry_points.txt
ocrd_tesserocr-0.20.1.dist-info/top_level.txt
ocrd_tesserocr-0.20.1.dist-info/RECORD
