Metadata-Version: 2.1
Name: ocrd_tesserocr
Version: 0.20.1
Summary: Preprocess, segment and recognize text using Tesseract OCR and the OCR-D framework
Author-email: Robert Sachunsky <sachunsky@informatik.uni-leipzig.de>, Konstantin Baierer <unixprog@gmail.com>, Kay-Michael Würzner <wuerzner@gmail.com>
License: Apache License 2.0
Project-URL: Homepage, https://github.com/OCR-D/ocrd_tesserocr
Project-URL: Repository, https://github.com/OCR-D/ocrd_tesserocr.git
Keywords: ocr,ocr-d,tesseract-ocr
Classifier: Development Status :: 5 - Production/Stable
Classifier: Environment :: Console
Classifier: Intended Audience :: Science/Research
Classifier: Intended Audience :: Other Audience
Classifier: License :: OSI Approved :: Apache Software License
Classifier: Programming Language :: Python :: 3
Classifier: Programming Language :: Python :: 3 :: Only
Classifier: Topic :: Text Processing
Requires-Python: >=3.8
License-File: LICENSE
Requires-Dist: ocrd>=3.0.2
Requires-Dist: click
Requires-Dist: tesserocr>=2.5.2
Requires-Dist: shapely>=2.0
Requires-Dist: scipy
Provides-Extra: test
Requires-Dist: pytest>=4.4.0; extra == "test"
Requires-Dist: pytest-xdist; extra == "test"
Requires-Dist: coverage>=4.5.2; extra == "test"
